moretest/__init__.py
moretest/entry.py
moretest-0.12.0.dist-info/entry_points.txt
moretest-0.12.0.dist-info/WHEEL
moretest-0.12.0.dist-info/METADATA
moretest-0.12.0.dist-info/RECORD
